_bentoml_impl/__init__.py
_bentoml_impl/arrow.py
_bentoml_impl/docker.py
_bentoml_impl/loader.py
_bentoml_impl/serde.py
_bentoml_impl/client/__init__.py
_bentoml_impl/client/base.py
_bentoml_impl/client/http.py
_bentoml_impl/client/proxy.py
_bentoml_impl/client/proxy2.py
_bentoml_impl/client/task.py
_bentoml_impl/frameworks/catboost.py
_bentoml_impl/frameworks/importer.py
_bentoml_impl/frameworks/lightgbm.py
_bentoml_impl/frameworks/mlflow.py
_bentoml_impl/frameworks/sklearn.py
_bentoml_impl/frameworks/xgboost.py
_bentoml_impl/server/.gitignore
_bentoml_impl/server/__init__.py
_bentoml_impl/server/allocator.py
_bentoml_impl/server/app.py
_bentoml_impl/server/main-openapi.html
_bentoml_impl/server/main-ui.html
_bentoml_impl/server/mount.py
_bentoml_impl/server/proxy.py
_bentoml_impl/server/serving.py
_bentoml_impl/tasks/__init__.py
_bentoml_impl/tasks/result.py
_bentoml_impl/tasks/serde.py
_bentoml_impl/worker/__init__.py
_bentoml_impl/worker/patch.py
_bentoml_impl/worker/runner.py
_bentoml_impl/worker/service.py
_bentoml_sdk/__init__.py
_bentoml_sdk/_internals.py
_bentoml_sdk/_pydantic.py
_bentoml_sdk/decorators.py
_bentoml_sdk/gradio.py
_bentoml_sdk/images.py
_bentoml_sdk/io_models.py
_bentoml_sdk/method.py
_bentoml_sdk/typing_utils.py
_bentoml_sdk/validators.py
_bentoml_sdk/models/__init__.py
_bentoml_sdk/models/base.py
_bentoml_sdk/models/huggingface.py
_bentoml_sdk/service/__init__.py
_bentoml_sdk/service/config.py
_bentoml_sdk/service/dependency.py
_bentoml_sdk/service/factory.py
_bentoml_sdk/service/openapi.py
bentoml/__init__.py
bentoml/__main__.py
bentoml/_version.py
bentoml/api_token.py
bentoml/batch.py
bentoml/bentos.py
bentoml/client.py
bentoml/cloud.py
bentoml/container.py
bentoml/deployment.py
bentoml/diffusers_simple.py
bentoml/exceptions.py
bentoml/gradio.py
bentoml/images.py
bentoml/io.py
bentoml/legacy.py
bentoml/metrics.py
bentoml/metrics.pyi
bentoml/models.py
bentoml/monitoring.py
bentoml/py.typed
bentoml/ray.py
bentoml/server.py
bentoml-1.4.34.dist-info/METADATA
bentoml-1.4.34.dist-info/WHEEL
bentoml-1.4.34.dist-info/entry_points.txt
bentoml-1.4.34.dist-info/licenses/LICENSE
bentoml-1.4.34.dist-info/RECORD
