Metadata-Version: 2.4
Name: bentoml
Version: 1.4.34
Summary: BentoML: The easiest way to serve AI apps and models
Project-URL: Homepage, https://bentoml.com
Project-URL: Documentation, https://docs.bentoml.com
Project-URL: GitHub, https://github.com/bentoml/bentoml
Project-URL: Twitter, https://twitter.com/bentomlai
Project-URL: Tracker, https://github.com/bentoml/BentoML/issues
Project-URL: Slack, https://l.bentoml.com/join-slack
Project-URL: Blog, https://bentoml.com/blog
Author-email: BentoML Team <contact@bentoml.com>
License: Apache-2.0
License-File: LICENSE
Keywords: BentoML,Compound AI Systems,LLMOps,MLOps,Model Deployment,Model Inference,Model Serving
Classifier: Development Status :: 5 - Production/Stable
Classifier: Intended Audience :: Developers
Classifier: Intended Audience :: Science/Research
Classifier: License :: OSI Approved :: Apache Software License
Classifier: Operating System :: OS Independent
Classifier: Programming Language :: Python :: 3
Classifier: Programming Language :: Python :: 3 :: Only
Classifier: Programming Language :: Python :: 3.9
Classifier: Programming Language :: Python :: 3.10
Classifier: Programming Language :: Python :: 3.11
Classifier: Programming Language :: Python :: 3.12
Classifier: Programming Language :: Python :: Implementation :: CPython
Classifier: Topic :: Scientific/Engineering :: Artificial Intelligence
Classifier: Topic :: Software Development :: Libraries
Requires-Python: >=3.9
Requires-Dist: a2wsgi>=1.10.7
Requires-Dist: aiohttp
Requires-Dist: aiohttp-asgi-connector>=1.1.2
Requires-Dist: aiosqlite>=0.20.0
Requires-Dist: attrs>=22.2.0
Requires-Dist: cattrs<23.2.0,>=22.1.0
Requires-Dist: click-option-group
Requires-Dist: click>=7.0
Requires-Dist: cloudpickle>=2.0.0
Requires-Dist: fsspec>=2025.7.0
Requires-Dist: httpx
Requires-Dist: httpx-ws>=0.6.0
Requires-Dist: jinja2>=3.0.1
Requires-Dist: kantoku>=0.18.3
Requires-Dist: numpy
Requires-Dist: nvidia-ml-py
Requires-Dist: opentelemetry-api~=1.20
Requires-Dist: opentelemetry-instrumentation-aiohttp-client~=0.41b0
Requires-Dist: opentelemetry-instrumentation-asgi~=0.41b0
Requires-Dist: opentelemetry-instrumentation~=0.41b0
Requires-Dist: opentelemetry-sdk~=1.20
Requires-Dist: opentelemetry-semantic-conventions~=0.41b0
Requires-Dist: opentelemetry-util-http~=0.41b0
Requires-Dist: packaging>=22.0
Requires-Dist: pathspec
Requires-Dist: pip-requirements-parser>=31.2.0
Requires-Dist: prometheus-client>=0.10.0
Requires-Dist: psutil
Requires-Dist: pydantic<3
Requires-Dist: python-dateutil
Requires-Dist: python-json-logger
Requires-Dist: python-multipart
Requires-Dist: pyyaml>=5.0
Requires-Dist: rich-toolkit>=0.15.1
Requires-Dist: rich>=11.2.0
Requires-Dist: schema
Requires-Dist: simple-di>=0.1.4
Requires-Dist: starlette>=0.24.0
Requires-Dist: tomli-w
Requires-Dist: tomli>=1.1.0; python_version < '3.11'
Requires-Dist: uvicorn>=0.22.0
Requires-Dist: watchfiles>=0.15.0
Provides-Extra: all
Requires-Dist: grpcio; extra == 'all'
Requires-Dist: grpcio-channelz; extra == 'all'
Requires-Dist: grpcio-health-checking; extra == 'all'
Requires-Dist: grpcio-reflection; extra == 'all'
Requires-Dist: opentelemetry-exporter-jaeger~=1.20; extra == 'all'
Requires-Dist: opentelemetry-exporter-otlp-proto-grpc~=1.20; extra == 'all'
Requires-Dist: opentelemetry-exporter-otlp-proto-http~=1.20; extra == 'all'
Requires-Dist: opentelemetry-exporter-otlp~=1.20; extra == 'all'
Requires-Dist: opentelemetry-exporter-zipkin~=1.20; extra == 'all'
Requires-Dist: opentelemetry-instrumentation-grpc~=0.41b0; extra == 'all'
Requires-Dist: pandas>=1; extra == 'all'
Requires-Dist: pillow; extra == 'all'
Requires-Dist: protobuf; extra == 'all'
Requires-Dist: pyarrow; extra == 'all'
Requires-Dist: s3fs; extra == 'all'
Provides-Extra: aws
Requires-Dist: s3fs; extra == 'aws'
Provides-Extra: grpc
Requires-Dist: grpcio; extra == 'grpc'
Requires-Dist: grpcio-health-checking; extra == 'grpc'
Requires-Dist: opentelemetry-instrumentation-grpc~=0.41b0; extra == 'grpc'
Requires-Dist: protobuf; extra == 'grpc'
Provides-Extra: grpc-channelz
Requires-Dist: grpcio; extra == 'grpc-channelz'
Requires-Dist: grpcio-channelz; extra == 'grpc-channelz'
Requires-Dist: grpcio-health-checking; extra == 'grpc-channelz'
Requires-Dist: opentelemetry-instrumentation-grpc~=0.41b0; extra == 'grpc-channelz'
Requires-Dist: protobuf; extra == 'grpc-channelz'
Provides-Extra: grpc-reflection
Requires-Dist: grpcio; extra == 'grpc-reflection'
Requires-Dist: grpcio-health-checking; extra == 'grpc-reflection'
Requires-Dist: grpcio-reflection; extra == 'grpc-reflection'
Requires-Dist: opentelemetry-instrumentation-grpc~=0.41b0; extra == 'grpc-reflection'
Requires-Dist: protobuf; extra == 'grpc-reflection'
Provides-Extra: io
Requires-Dist: pandas>=1; extra == 'io'
Requires-Dist: pillow; extra == 'io'
Requires-Dist: pyarrow; extra == 'io'
Provides-Extra: io-image
Requires-Dist: pillow; extra == 'io-image'
Provides-Extra: io-pandas
Requires-Dist: pandas>=1; extra == 'io-pandas'
Requires-Dist: pyarrow; extra == 'io-pandas'
Provides-Extra: monitor-otlp
Requires-Dist: opentelemetry-exporter-otlp-proto-grpc~=1.20; extra == 'monitor-otlp'
Requires-Dist: opentelemetry-exporter-otlp-proto-http~=1.20; extra == 'monitor-otlp'
Provides-Extra: tracing
Requires-Dist: opentelemetry-exporter-jaeger~=1.20; extra == 'tracing'
Requires-Dist: opentelemetry-exporter-otlp~=1.20; extra == 'tracing'
Requires-Dist: opentelemetry-exporter-zipkin~=1.20; extra == 'tracing'
Provides-Extra: tracing-jaeger
Requires-Dist: opentelemetry-exporter-jaeger~=1.20; extra == 'tracing-jaeger'
Provides-Extra: tracing-otlp
Requires-Dist: opentelemetry-exporter-otlp~=1.20; extra == 'tracing-otlp'
Provides-Extra: tracing-zipkin
Requires-Dist: opentelemetry-exporter-zipkin~=1.20; extra == 'tracing-zipkin'
Provides-Extra: triton
Requires-Dist: tritonclient>=2.29.0; extra == 'triton'
Requires-Dist: tritonclient[all]; (sys_platform != 'darwin') and extra == 'triton'
Provides-Extra: unsloth
Requires-Dist: bentoml-unsloth>=0.1.0; extra == 'unsloth'
